neuroptica/__init__.py
neuroptica/component_layers.py
neuroptica/components.py
neuroptica/initializers.py
neuroptica/layers.py
neuroptica/losses.py
neuroptica/models.py
neuroptica/nonlinearities.py
neuroptica/optimizers.py
neuroptica/settings.py
neuroptica/utils.py
tests/__init__.py
tests/base.py
tests/test_components.py
tests/test_layers.py
tests/test_losses.py
tests/test_models.py
tests/test_nonlinearities.py
tests/test_optimizers.py
neuroptica-0.1.0.dist-info/LICENSE
neuroptica-0.1.0.dist-info/METADATA
neuroptica-0.1.0.dist-info/WHEEL
neuroptica-0.1.0.dist-info/top_level.txt
neuroptica-0.1.0.dist-info/RECORD
