Metadata-Version: 2.1
Name: neuroptica
Version: 0.1.0
Summary: Nanophotonic Neural Network Simulator
Home-page: https://github.com/fancompute/neuroptica
Author: Ben Bartlett
Author-email: benbartlett@stanford.edu
License: MIT
Platform: UNKNOWN
Classifier: Programming Language :: Python :: 3
Classifier: Operating System :: OS Independent
Requires-Dist: numpy
Requires-Dist: scipy
Requires-Dist: numba
Requires-Dist: tqdm
